in_place/__init__.py
in_place/py.typed
in_place-1.0.1.dist-info/METADATA
in_place-1.0.1.dist-info/WHEEL
in_place-1.0.1.dist-info/licenses/LICENSE
in_place-1.0.1.dist-info/RECORD
