Metadata-Version: 2.3
Name: in_place
Version: 1.0.1
Summary: In-place file processing
Project-URL: Source Code, https://github.com/jwodder/inplace
Project-URL: Bug Tracker, https://github.com/jwodder/inplace/issues
Author-email: John Thorvald Wodder II <inplace@varonathe.org>
License: MIT
Keywords: file,fileinput,in-place,inplace,io,open,redirection,sed,tempfile,tmpfile
Classifier: Intended Audience :: Developers
Classifier: License :: OSI Approved :: MIT License
Classifier: Programming Language :: Python :: 3
Classifier: Programming Language :: Python :: 3 :: Only
Classifier: Programming Language :: Python :: 3.8
Classifier: Programming Language :: Python :: 3.9
Classifier: Programming Language :: Python :: 3.10
Classifier: Programming Language :: Python :: 3.11
Classifier: Programming Language :: Python :: 3.12
Classifier: Programming Language :: Python :: 3.13
Classifier: Programming Language :: Python :: Implementation :: CPython
Classifier: Programming Language :: Python :: Implementation :: PyPy
Classifier: Topic :: System :: Filesystems
Classifier: Topic :: Text Processing :: Filters
Classifier: Typing :: Typed
Requires-Python: >=3.8
